llbase/__init__.py
llbase/config.py
llbase/fastest_elementtree.py
llbase/llidl.py
llbase/lljsonlog.py
llbase/llrest.py
llbase/llsd.py
llbase/lluuid.py
llbase/tkrestservice.py
llbase-1.3.1.dist-info/LICENSE
llbase-1.3.1.dist-info/METADATA
llbase-1.3.1.dist-info/WHEEL
llbase-1.3.1.dist-info/top_level.txt
llbase-1.3.1.dist-info/RECORD
